[
	{
		"type":"BUS", //TROLLEYBUS
		"name":"25в",
		"code":"a25v", //t10 для троллейбуса
		"directions": [
			{
				"isForward" : true, // true | false - для различия направлений туда-обратно
				"name" : "Медгородок - Предприятие «Ратон»",
				"routePoints" : [
					{
						"position" : 1,
						"name" : "Медгородок",
						"schedules" : [
							{
								"days": "12345", //номера дней недели
								"times" : ["05:59", "06:12", "06:26"]
							},
							{
								"days": "67", //выходные
								"times" : ["05:59", "06:12", "06:26"]
							}
						]
					}
				]
			}
		]
	}
]